riotctrl/__init__.py
riotctrl/ctrl.py
riotctrl/shell/__init__.py
riotctrl/shell/json.py
riotctrl/tests/__init__.py
riotctrl/tests/ctrl_test.py
riotctrl/tests/riotctrl_test.py
riotctrl/tests/shell_json_test.py
riotctrl/tests/shell_test.py
riotctrl-0.5.1.dist-info/licenses/LICENSE
riotctrl-0.5.1.dist-info/METADATA
riotctrl-0.5.1.dist-info/WHEEL
riotctrl-0.5.1.dist-info/top_level.txt
riotctrl-0.5.1.dist-info/RECORD
