Metadata-Version: 2.4
Name: riotctrl
Version: 0.5.1
Summary: RIOT Ctrl - A RIOT node python abstraction
Home-page: https://github.com/RIOT-OS/riotctrl
Download-URL: https://github.com/RIOT-OS/riotctrl
Author: Gaëtan Harter, Leandro Lanzieri, Martine S. Lenders
Author-email: gaetan.harter@fu-berlin.de, leandro.lanzieri@haw-hamburg.de, m.lenders@fu-berlin.de
License: MIT
Classifier: Development Status :: 2 - Pre-Alpha
Classifier: Programming Language :: Python
Classifier: Programming Language :: Python :: 3
Classifier: Programming Language :: Python :: 3.5
Classifier: Programming Language :: Python :: 3.6
Classifier: Programming Language :: Python :: 3.7
Classifier: Programming Language :: Python :: 3.8
Classifier: Programming Language :: Python :: 3.9
Classifier: Intended Audience :: End Users/Desktop
Classifier: Environment :: Console
Classifier: Topic :: Utilities
Requires-Python: >=3.5
License-File: LICENSE
Requires-Dist: pexpect>=4.7
Requires-Dist: psutil
Provides-Extra: rapidjson
Requires-Dist: python-rapidjson; extra == "rapidjson"
Dynamic: author
Dynamic: author-email
Dynamic: classifier
Dynamic: description
Dynamic: description-content-type
Dynamic: download-url
Dynamic: home-page
Dynamic: license
Dynamic: license-file
Dynamic: provides-extra
Dynamic: requires-dist
Dynamic: requires-python
Dynamic: summary
